cloj/__init__.py
cloj/funcs.py
cloj-0.2.0.dist-info/LICENSE.md
cloj-0.2.0.dist-info/WHEEL
cloj-0.2.0.dist-info/METADATA
cloj-0.2.0.dist-info/RECORD
