Metadata-Version: 2.1
Name: cloj
Version: 0.2.0
Summary: Clojure inspired helper functions
Home-page: https://github.com/licht1stein/cloj
License: MIT
Author: MB
Author-email: mb@blaster.ai
Requires-Python: >=3.6,<4.0
Classifier: License :: OSI Approved :: MIT License
Classifier: Programming Language :: Python :: 3
Classifier: Programming Language :: Python :: 3.6
Classifier: Programming Language :: Python :: 3.7
Classifier: Programming Language :: Python :: 3.8
Classifier: Programming Language :: Python :: 3.9
